mosaik_components/__init__.py
mosaik_components/heatpump/Heat_Pump_Design.py
mosaik_components/heatpump/Heat_Pump_Model.py
mosaik_components/heatpump/Heat_Pump_mosaik.py
mosaik_components/heatpump/__init__.py
mosaik_components/heatpump/controller/__init__.py
mosaik_components/heatpump/controller/controller.py
mosaik_components/heatpump/controller/controller_mosaik.py
mosaik_components/heatpump/coolingloadsim/coolingloadsim.py
mosaik_components/heatpump/coolingloadsim/coolingloadsim_mosaik.py
mosaik_components/heatpump/cop_m_data.json
mosaik_components/heatpump/eta_s_data.json
mosaik_components/heatpump/hotwatertank/__init__.py
mosaik_components/heatpump/hotwatertank/hotwatertank.py
mosaik_components/heatpump/hotwatertank/hotwatertank_mosaik.py
mosaik_heatpump-1.0.2.dist-info/AUTHORS.txt
mosaik_heatpump-1.0.2.dist-info/LICENSE
mosaik_heatpump-1.0.2.dist-info/METADATA
mosaik_heatpump-1.0.2.dist-info/WHEEL
mosaik_heatpump-1.0.2.dist-info/RECORD
