Metadata-Version: 2.1
Name: mosaik-heatpump
Version: 1.0.2
Summary: mosaik-heatpump provides models for the simulation of heating systems
License: MIT
Author: Pranay Kasturi
Author-email: mosaik@offis.de
Requires-Python: >=3.8,<4
Classifier: License :: OSI Approved :: MIT License
Classifier: Programming Language :: Python :: 3
Classifier: Programming Language :: Python :: 3.8
Classifier: Programming Language :: Python :: 3.9
Classifier: Programming Language :: Python :: 3.10
Classifier: Programming Language :: Python :: 3.11
Classifier: Programming Language :: Python :: 3.12
Requires-Dist: hplib (>=1.9,<2.0)
Requires-Dist: mosaik-api-v3 (>=3.0.4)
Requires-Dist: tespy (>=0.4.2,<0.7.0)
